localsee/__init__.py
localsee/__main__.py
localsee/api.py
localsee/localsee.py
localsee/option.py
localsee/scripts/__init__.py
localsee/scripts/xyscript.py
localsee_amadeus-0.1.7.dist-info/LICENSE
localsee_amadeus-0.1.7.dist-info/METADATA
localsee_amadeus-0.1.7.dist-info/WHEEL
localsee_amadeus-0.1.7.dist-info/top_level.txt
localsee_amadeus-0.1.7.dist-info/RECORD
