Metadata-Version: 2.1
Name: localsee-amadeus
Version: 0.1.7
Summary: An image local detail shower
Home-page: https://github.com/Amadeus9029/localshower
Author: Amadeus9029
Author-email: 965720890@qq.com
License: UNKNOWN
Platform: UNKNOWN
Classifier: Programming Language :: Python :: 3
Classifier: License :: OSI Approved :: MIT License
Classifier: Operating System :: OS Independent
Requires-Dist: elogger-amadeus (>=0.0.1)
Requires-Dist: opencv-python (>=3.4.1)
